odoo/addons/mass/README.rst
odoo/addons/mass/__init__.py
odoo/addons/mass/__manifest__.py
odoo/addons/mass/data/mass_data.xml
odoo/addons/mass/demo/mass_demo.xml
odoo/addons/mass/i18n/fr.po
odoo/addons/mass/i18n/it.po
odoo/addons/mass/i18n/mass.pot
odoo/addons/mass/models/__init__.py
odoo/addons/mass/models/mass.py
odoo/addons/mass/models/product.py
odoo/addons/mass/models/res_company.py
odoo/addons/mass/models/res_partner.py
odoo/addons/mass/readme/CONFIGURE.rst
odoo/addons/mass/readme/CONTRIBUTORS.rst
odoo/addons/mass/readme/DESCRIPTION.rst
odoo/addons/mass/readme/USAGE.rst
odoo/addons/mass/report/report.xml
odoo/addons/mass/report/report_massline.xml
odoo/addons/mass/report/report_massrequesttransfer.xml
odoo/addons/mass/security/ir.model.access.csv
odoo/addons/mass/security/mass_security.xml
odoo/addons/mass/static/description/icon.png
odoo/addons/mass/static/description/index.html
odoo/addons/mass/tests/__init__.py
odoo/addons/mass/tests/test_generate_mass_journal.py
odoo/addons/mass/views/mass.xml
odoo/addons/mass/views/product.xml
odoo/addons/mass/views/res_partner.xml
odoo/addons/mass/wizard/__init__.py
odoo/addons/mass/wizard/mass_journal_generate.py
odoo/addons/mass/wizard/mass_journal_generate_view.xml
odoo/addons/mass/wizard/mass_journal_validate.py
odoo/addons/mass/wizard/mass_journal_validate_view.xml
odoo/addons/mass/wizard/res_config_settings.py
odoo/addons/mass/wizard/res_config_settings_view.xml
odoo/addons/mass/wizard/swap_celebrant.py
odoo/addons/mass/wizard/swap_celebrant_view.xml
odoo14_addon_mass-14.0.1.4.0.dist-info/METADATA
odoo14_addon_mass-14.0.1.4.0.dist-info/WHEEL
odoo14_addon_mass-14.0.1.4.0.dist-info/top_level.txt
odoo14_addon_mass-14.0.1.4.0.dist-info/RECORD
